Checkpoint 2/SimonControl.v
//==============================================================================
// Control Module for Simon Project
//==============================================================================

module SimonControl(
	// External Inputs
	input        clk,           // Clock
	input        rst,           // Reset

	// Datapath Inputs
	// input     localin1,
	input valid,
	input n_tc,
	input of_out,
	input last_it,
	input p_correct,

	// Datapath Control Outputs
	// output    control1,
	output reg p_write,
	output reg n_inc,
	output reg i_clr,
	output reg i_inc,
	output reg of_set,
	output reg psi_ld,
	output reg reset,
	output reg p_reflect,

	// External Outputs
	// output [2:0] mode_leds
	output reg [2:0] mode_leds
);

	// Declare Local Vars Here
	// reg [X:0] state;
	// reg [X:0] next_state;
	reg [1:0] state;
	reg [1:0] next_state;

	// LED Light Parameters
	localparam LED_MODE_INPUT    = 3'b001;
	localparam LED_MODE_PLAYBACK = 3'b010;
	localparam LED_MODE_REPEAT   = 3'b100;
	localparam LED_MODE_DONE     = 3'b111;

	// Declare State Names Here
	//localparam STATE_ONE = 2'd0;
	localparam STATE_INPUT = 2'd0;
	localparam STATE_PLAYBACK = 2'd1;
	localparam STATE_REPEAT = 2'd2;
	localparam STATE_DONE = 2'd3;

	// Output Combinational Logic
	always @( * ) begin
		// Set defaults
		// signal_one = 0; ...
		p_write = 0;
		n_inc = 0;
		i_clr = 0;
		i_inc = 0;
		of_set = 0;
		psi_ld = 0;
		reset = rst;
		p_reflect = 1;
		mode_leds = 0;


		// Write your output logic here
		case (state)
			STATE_INPUT: begin
				mode_leds = LED_MODE_INPUT;
				p_reflect = 1;
				if (~rst) begin
					p_write = valid;
					n_inc = valid;
					i_clr = 1;
					of_set = of_out | (valid & n_tc);
					psi_ld = of_out;
				end
			end
			STATE_PLAYBACK: begin
				mode_leds = LED_MODE_PLAYBACK;
				p_reflect = 0;
				if (~rst) begin
					i_clr = last_it;
					i_inc = ~last_it;
				end
			end
			STATE_REPEAT: begin
				mode_leds = LED_MODE_REPEAT;
				p_reflect = 1;
				if (~rst) begin
					i_clr = ~p_correct;
					i_inc = p_correct;
				end
			end
			STATE_DONE: begin
				mode_leds = LED_MODE_DONE;
				p_reflect = 0;
				if (~rst) begin
					i_clr = last_it;
					i_inc = ~last_it;
				end
			end
		endcase
		
	end

	// Next State Combinational Logic
	always @( * ) begin
		// Write your Next State Logic Here
		// next_state = ???
		next_state = state;
		
		case (state)
			STATE_INPUT: begin
				if (valid) begin
					next_state = STATE_PLAYBACK;
				end
			end
			STATE_PLAYBACK: begin
				if (last_it) begin
					next_state = STATE_REPEAT;
				end
			end
			STATE_REPEAT: begin
				if (~p_correct) begin
					next_state = STATE_DONE;
				end
				else if (last_it & p_correct) begin
					next_state = STATE_INPUT;
				end
			end
		endcase
		
	end

	// State Update Sequential Logic
	always @(posedge clk) begin
		if (rst) begin
			// Update state to reset state
			// state <= STATE_ONE;
			state <= STATE_INPUT;
		end
		else begin
			// Update state to next state
			// state <= next_state;
			state <= next_state;
		end
	end

endmodule

Checkpoint 2/SimonControl.t.v
//===============================================================================
// Testbench Module for Simon Controller
//===============================================================================
`timescale 1ns/100ps

`include "SimonControl.v"

// Print an error message (MSG) if value ONE is not equal
// to value TWO.
`define ASSERT_EQ(ONE, TWO, MSG)               \
	begin                                      \
		if ((ONE) !== (TWO)) begin             \
			$display("\t\t[FAILURE]:%s", (MSG)); \
		end                                    \
	end #0

// Set the variable VAR to the value VALUE, printing a notification
// to the screen indicating the variable's update.
// The setting of the variable is preceeded and followed by
// a 1-timestep delay.
`define SET(VAR, VALUE) $display("\tSetting %s to %s...", "VAR", "VALUE"); #1; VAR = (VALUE); #1

// Cycle the clock up and then down, simulating
// a button press.
`define CLOCK $display("\tPressing uclk..."); #1; clk = 1; #1; clk = 0; #1

module SimonControlTest;

	// Local Vars
	reg clk = 0;
	reg rst = 0;
	// More vars here...
	reg valid = 0;
	reg n_tc = 0;
	reg of_out = 0;
	reg last_it = 0;
	reg p_correct = 0;
	
	wire p_write;
	wire n_inc;
	wire i_clr;
	wire i_inc;
	wire of_set;
	wire psi_ld;
	wire reset;
	wire p_reflect;
	
	wire [2:0] mode_leds;



	// LED Light Parameters
	localparam LED_MODE_INPUT    = 3'b001;
	localparam LED_MODE_PLAYBACK = 3'b010;
	localparam LED_MODE_REPEAT   = 3'b100;
	localparam LED_MODE_DONE     = 3'b111;

	// VCD Dump
	initial begin
		$dumpfile("SimonControlTest.vcd");
		$dumpvars;
	end

	// Simon Control Module
	SimonControl ctrl(
		.clk (clk),
		.rst (rst),

		// More ports here...
		.valid (valid),
		.n_tc (n_tc),
		.of_out (of_out),
		.last_it (last_it),
		.p_correct (p_correct),
		
		.p_write (p_write),
		.n_inc (n_inc),
		.i_clr (i_clr),
		.i_inc (i_inc),
		.of_set (of_set),
		.psi_ld (psi_ld),
		.reset (reset),
		.p_reflect (p_reflect),
		
		.mode_leds(mode_leds)

	);

	// Main Test Logic
	initial begin
		// Reset the game
		`SET(rst, 1);
		`CLOCK;
		`SET(rst, 0);

		// Your Test Logic Here
		// Check input defaults
		$display("Block 1");
		`ASSERT_EQ(mode_leds, LED_MODE_INPUT, "a");
		`ASSERT_EQ(p_reflect, 1, "b");
		`ASSERT_EQ(p_write, 0, "c");
		`ASSERT_EQ(n_inc, 0, "d");
		`ASSERT_EQ(i_inc, 0, "e");
		`ASSERT_EQ(i_clr, 1, "f");
		`ASSERT_EQ(of_set, 0, "g");
		`ASSERT_EQ(psi_ld, 0, "h");
		`ASSERT_EQ(reset, 0, "i");
		
		// check valid = 1
		$display("Block 2");
		`SET(valid, 1);
		`ASSERT_EQ(mode_leds, LED_MODE_INPUT, "a");
		`ASSERT_EQ(p_reflect, 1, "b");
		`ASSERT_EQ(p_write, 1, "c");
		`ASSERT_EQ(n_inc, 1, "d");
		`ASSERT_EQ(i_inc, 0, "e");
		`ASSERT_EQ(i_clr, 1, "f");
		`ASSERT_EQ(of_set, 0, "g");
		`ASSERT_EQ(psi_ld, 0, "h");
		`ASSERT_EQ(reset, 0, "i");
		
		// check valid and n_tc = 1
		$display("Block 3");
		`SET(n_tc, 1);
		`ASSERT_EQ(mode_leds, LED_MODE_INPUT, "a");
		`ASSERT_EQ(p_reflect, 1, "b");
		`ASSERT_EQ(p_write, 1, "c");
		`ASSERT_EQ(n_inc, 1, "d");
		`ASSERT_EQ(i_inc, 0, "e");
		`ASSERT_EQ(i_clr, 1, "f");
		`ASSERT_EQ(of_set, 1, "g");
		`ASSERT_EQ(psi_ld, 0, "h");
		`ASSERT_EQ(reset, 0, "i");
		
		// check of_out = 1
		$display("Block 4");
		`SET(valid, 0);
		`SET(n_tc, 0);
		`SET(of_out, 1);
		`ASSERT_EQ(mode_leds, LED_MODE_INPUT, "a");
		`ASSERT_EQ(p_reflect, 1, "b");
		`ASSERT_EQ(p_write, 0, "c");
		`ASSERT_EQ(n_inc, 0, "d");
		`ASSERT_EQ(i_inc, 0, "e");
		`ASSERT_EQ(i_clr, 1, "f");
		`ASSERT_EQ(of_set, 1, "g");
		`ASSERT_EQ(psi_ld, 1, "h");
		`ASSERT_EQ(reset, 0, "i");
		
		// check all but reset
		$display("Block 5");
		`SET(valid, 1);
		`SET(n_tc, 1);
		`SET(of_out, 1);
		`ASSERT_EQ(mode_leds, LED_MODE_INPUT, "a");
		`ASSERT_EQ(p_reflect, 1, "b");
		`ASSERT_EQ(p_write, 1, "c");
		`ASSERT_EQ(n_inc, 1, "d");
		`ASSERT_EQ(i_inc, 0, "e");
		`ASSERT_EQ(i_clr, 1, "f");
		`ASSERT_EQ(of_set, 1, "g");
		`ASSERT_EQ(psi_ld, 1, "h");
		`ASSERT_EQ(reset, 0, "i");
		
		// check all w/ reset
		$display("Block 6");
		`SET(rst, 1);
		`ASSERT_EQ(mode_leds, LED_MODE_INPUT, "a");
		`ASSERT_EQ(p_reflect, 1, "b");
		`ASSERT_EQ(p_write, 0, "c");
		`ASSERT_EQ(n_inc, 0, "d");
		`ASSERT_EQ(i_inc, 0, "e");
		`ASSERT_EQ(i_clr, 0, "f");
		`ASSERT_EQ(of_set, 0, "g");
		`ASSERT_EQ(psi_ld, 0, "h");
		`ASSERT_EQ(reset, 1, "i");
		
		// check button press while not valid
		$display("Block 7");
		`SET(rst, 0);
		`SET(valid, 0);
		`SET(n_tc, 0);
		`SET(of_out, 0);
		`CLOCK;
		`ASSERT_EQ(mode_leds, LED_MODE_INPUT, "a");
		`ASSERT_EQ(p_reflect, 1, "b");
		`ASSERT_EQ(p_write, 0, "c");
		`ASSERT_EQ(n_inc, 0, "d");
		`ASSERT_EQ(i_inc, 0, "e");
		`ASSERT_EQ(i_clr, 1, "f");
		`ASSERT_EQ(of_set, 0, "g");
		`ASSERT_EQ(psi_ld, 0, "h");
		`ASSERT_EQ(reset, 0, "i");
		
		// check button press while valid
		$display("Block 8");
		`SET(valid, 1);
		`CLOCK;
		`ASSERT_EQ(mode_leds, LED_MODE_PLAYBACK, "a");
		`ASSERT_EQ(p_reflect, 0, "b");
		`ASSERT_EQ(p_write, 0, "c");
		`ASSERT_EQ(n_inc, 0, "d");
		`ASSERT_EQ(i_inc, 1, "e");
		`ASSERT_EQ(i_clr, 0, "f");
		`ASSERT_EQ(of_set, 0, "g");
		`ASSERT_EQ(psi_ld, 0, "h");
		`ASSERT_EQ(reset, 0, "i");
		
		// check last_it = 1
		$display("Block 9");
		`SET(last_it, 1);
		`ASSERT_EQ(mode_leds, LED_MODE_PLAYBACK, "a");
		`ASSERT_EQ(p_reflect, 0, "b");
		`ASSERT_EQ(p_write, 0, "c");
		`ASSERT_EQ(n_inc, 0, "d");
		`ASSERT_EQ(i_inc, 0, "e");
		`ASSERT_EQ(i_clr, 1, "f");
		`ASSERT_EQ(of_set, 0, "g");
		`ASSERT_EQ(psi_ld, 0, "h");
		`ASSERT_EQ(reset, 0, "i");
		
		// check reset
		$display("Block 10");
		`SET(rst, 1);
		`ASSERT_EQ(mode_leds, LED_MODE_PLAYBACK, "a");
		`ASSERT_EQ(p_reflect, 0, "b");
		`ASSERT_EQ(p_write, 0, "c");
		`ASSERT_EQ(n_inc, 0, "d");
		`ASSERT_EQ(i_inc, 0, "e");
		`ASSERT_EQ(i_clr, 0, "f");
		`ASSERT_EQ(of_set, 0, "g");
		`ASSERT_EQ(psi_ld, 0, "h");
		`ASSERT_EQ(reset, 1, "i");
		
		// check button press w/ last_it = 0
		$display("Block 11");
		`SET(rst, 0);
		`SET(last_it, 0);
		`CLOCK;
		`ASSERT_EQ(mode_leds, LED_MODE_PLAYBACK, "a");
		`ASSERT_EQ(p_reflect, 0, "b");
		`ASSERT_EQ(p_write, 0, "c");
		`ASSERT_EQ(n_inc, 0, "d");
		`ASSERT_EQ(i_inc, 1, "e");
		`ASSERT_EQ(i_clr, 0, "f");
		`ASSERT_EQ(of_set, 0, "g");
		`ASSERT_EQ(psi_ld, 0, "h");
		`ASSERT_EQ(reset, 0, "i");
		
		// check button press w/ last_it = 1
		$display("Block 12");
		`SET(last_it, 1);
		`CLOCK;
		`ASSERT_EQ(mode_leds, LED_MODE_REPEAT, "a");
		`ASSERT_EQ(p_reflect, 1, "b");
		`ASSERT_EQ(p_write, 0, "c");
		`ASSERT_EQ(n_inc, 0, "d");
		`ASSERT_EQ(i_inc, 0, "e");
		`ASSERT_EQ(i_clr, 1, "f");
		`ASSERT_EQ(of_set, 0, "g");
		`ASSERT_EQ(psi_ld, 0, "h");
		`ASSERT_EQ(reset, 0, "i");
		
		// check p_correct = 1
		$display("Block 13");
		`SET(p_correct, 1);
		`ASSERT_EQ(mode_leds, LED_MODE_REPEAT, "a");
		`ASSERT_EQ(p_reflect, 1, "b");
		`ASSERT_EQ(p_write, 0, "c");
		`ASSERT_EQ(n_inc, 0, "d");
		`ASSERT_EQ(i_inc, 1, "e");
		`ASSERT_EQ(i_clr, 0, "f");
		`ASSERT_EQ(of_set, 0, "");
		`ASSERT_EQ(psi_ld, 0, "");
		`ASSERT_EQ(reset, 0, "");
		
		// check reset
		$display("Block 14");
		`SET(rst, 1);
		`ASSERT_EQ(mode_leds, LED_MODE_REPEAT, "a");
		`ASSERT_EQ(p_reflect, 1, "b");
		`ASSERT_EQ(p_write, 0, "c");
		`ASSERT_EQ(n_inc, 0, "d");
		`ASSERT_EQ(i_inc, 0, "e");
		`ASSERT_EQ(i_clr, 0, "f");
		`ASSERT_EQ(of_set, 0, "g");
		`ASSERT_EQ(psi_ld, 0, "h");
		`ASSERT_EQ(reset, 1, "i");
		
		// check button press w/ last_it = 0 and p_correct = 1
		$display("Block 15");
		`SET(rst, 0);
		`SET(last_it, 0);
		`SET(p_correct, 1);
		`CLOCK;
		`ASSERT_EQ(mode_leds, LED_MODE_REPEAT, "a");
		`ASSERT_EQ(p_reflect, 1, "b");
		`ASSERT_EQ(p_write, 0, "c");
		`ASSERT_EQ(n_inc, 0, "d");
		`ASSERT_EQ(i_inc, 1, "e");
		`ASSERT_EQ(i_clr, 0, "f");
		`ASSERT_EQ(of_set, 0, "g");
		`ASSERT_EQ(psi_ld, 0, "h");
		`ASSERT_EQ(reset, 0, "i");
		
		// check button press w/ last_it = 1 and p_correct = 1
		$display("Block 16");
		`SET(last_it, 1);
		`CLOCK;
		`SET(valid, 0);
		`ASSERT_EQ(mode_leds, LED_MODE_INPUT, "a");
		`ASSERT_EQ(p_reflect, 1, "b");
		`ASSERT_EQ(p_write, 0, "c");
		`ASSERT_EQ(n_inc, 0, "d");
		`ASSERT_EQ(i_inc, 0, "e");
		`ASSERT_EQ(i_clr, 1, "f");
		`ASSERT_EQ(of_set, 0, "g");
		`ASSERT_EQ(psi_ld, 0, "h");
		`ASSERT_EQ(reset, 0, "i");
		
		// cycle back to repeat mode
		$display("Block 17");
		`SET(valid, 1);
		`CLOCK;
		`SET(last_it, 1);
		`CLOCK;
		`SET(p_correct, 0);
		`ASSERT_EQ(mode_leds, LED_MODE_REPEAT, "a");
		`ASSERT_EQ(p_reflect, 1, "b");
		`ASSERT_EQ(p_write, 0, "c");
		`ASSERT_EQ(n_inc, 0, "d");
		`ASSERT_EQ(i_inc, 0, "e");
		`ASSERT_EQ(i_clr, 1, "f");
		`ASSERT_EQ(of_set, 0, "g");
		`ASSERT_EQ(psi_ld, 0, "h");
		`ASSERT_EQ(reset, 0, "i");
		
		// check button press w/ p_correct = 0
		$display("Block 18");
		`CLOCK;
		`SET(last_it, 0);
		`ASSERT_EQ(mode_leds, LED_MODE_DONE, "a");
		`ASSERT_EQ(p_reflect, 0, "b");
		`ASSERT_EQ(p_write, 0, "c");
		`ASSERT_EQ(n_inc, 0, "d");
		`ASSERT_EQ(i_inc, 1, "e");
		`ASSERT_EQ(i_clr, 0, "f");
		`ASSERT_EQ(of_set, 0, "g");
		`ASSERT_EQ(psi_ld, 0, "h");
		`ASSERT_EQ(reset, 0, "i");
		
		// check last_it = 1
		$display("Block 18.5");
		`SET(last_it, 1);
		`ASSERT_EQ(mode_leds, LED_MODE_DONE, "a");
		`ASSERT_EQ(p_reflect, 0, "b");
		`ASSERT_EQ(p_write, 0, "c");
		`ASSERT_EQ(n_inc, 0, "d");
		`ASSERT_EQ(i_inc, 0, "e");
		`ASSERT_EQ(i_clr, 1, "f");
		`ASSERT_EQ(of_set, 0, "g");
		`ASSERT_EQ(psi_ld, 0, "h");
		`ASSERT_EQ(reset, 0, "i");
		
		// check reset
		$display("Block 19");
		`SET(rst, 1);
		`ASSERT_EQ(mode_leds, LED_MODE_DONE, "a");
		`ASSERT_EQ(p_reflect, 0, "b");
		`ASSERT_EQ(p_write, 0, "c");
		`ASSERT_EQ(n_inc, 0, "d");
		`ASSERT_EQ(i_inc, 0, "e");
		`ASSERT_EQ(i_clr, 0, "f");
		`ASSERT_EQ(of_set, 0, "g");
		`ASSERT_EQ(psi_ld, 0, "h");
		`ASSERT_EQ(reset, 1, "i");
		
		// button press
		$display("Block 20");
		`CLOCK;
		`SET(rst, 0);
		`SET(valid, 0);
		`ASSERT_EQ(mode_leds, LED_MODE_INPUT, "a");
		`ASSERT_EQ(p_reflect, 1, "b");
		`ASSERT_EQ(p_write, 0, "c");
		`ASSERT_EQ(n_inc, 0, "d");
		`ASSERT_EQ(i_inc, 0, "e");
		`ASSERT_EQ(i_clr, 1, "f");
		`ASSERT_EQ(of_set, 0, "g");
		`ASSERT_EQ(psi_ld, 0, "h");
		`ASSERT_EQ(reset, 0, "i");
		$finish;
	end

endmodule

simon/SimonControlTest.vcd
$date
	Tue Nov 24 01:51:50 2015
$end
$version
	Icarus Verilog
$end
$timescale
	100ps
$end
$scope module SimonControlTest $end
$var wire 1 ! i_clr $end
$var wire 1 " i_inc $end
$var wire 3 # mode_leds [2:0] $end
$var wire 1 $ n_inc $end
$var wire 1 % of_set $end
$var wire 1 & p_reflect $end
$var wire 1 ' p_write $end
$var wire 1 ( psi_ld $end
$var wire 1 ) reset $end
$var reg 1 * clk $end
$var reg 1 + last_it $end
$var reg 1 , n_tc $end
$var reg 1 - of_out $end
$var reg 1 . p_correct $end
$var reg 1 / rst $end
$var reg 1 0 valid $end
$scope module ctrl $end
$var wire 1 1 clk $end
$var wire 1 2 last_it $end
$var wire 1 3 n_tc $end
$var wire 1 4 of_out $end
$var wire 1 5 p_correct $end
$var wire 1 6 rst $end
$var wire 1 7 valid $end
$var reg 1 8 i_clr $end
$var reg 1 9 i_inc $end
$var reg 3 : mode_leds [2:0] $end
$var reg 1 ; n_inc $end
$var reg 2 < next_state [1:0] $end
$var reg 1 = of_set $end
$var reg 1 > p_reflect $end
$var reg 1 ? p_write $end
$var reg 1 @ psi_ld $end
$var reg 1 A reset $end
$var reg 2 B state [1:0] $end
$upscope $end
$upscope $end
$enddefinitions $end
#0
$dumpvars
bx B
0A
0@
0?
1>
0=
bx <
0;
b0 :
09
08
07
06
05
04
03
02
01
00
0/
0.
0-
0,
0+
0*
0)
0(
0'
1&
0%
0$
b0 #
0"
0!
$end
#10
1A
1)
1/
16
#30
b0 <
b1 :
b1 #
b0 B
1*
11
#40
0*
01
#60
18
1!
b1 :
b1 #
0A
0)
0/
06
#80
b1 <
1;
1$
1?
1'
b1 :
b1 #
18
1!
10
17
#100
1=
1%
b1 :
b1 #
18
1!
1;
1$
1?
1'
1,
13
#120
b0 <
b1 :
b1 #
0=
0%
18
1!
0;
0$
0?
0'
00
07
#140
b1 :
b1 #
18
1!
0,
03
#160
1@
1(
1=
1%
b1 :
b1 #
18
1!
1-
14
#180
b1 <
1;
1$
1?
1'
b1 :
b1 #
1@
1(
1=
1%
18
1!
10
17
#200
b1 :
b1 #
1@
1(
1=
1%
18
1!
1;
1$
1?
1'
1,
13
#240
b1 :
b1 #
1A
1)
0@
0(
0=
0%
08
0!
0;
0$
0?
0'
1/
16
#260
1@
1(
1=
1%
18
1!
1;
1$
1?
1'
b1 :
b1 #
0A
0)
0/
06
#280
b0 <
b1 :
b1 #
1@
1(
1=
1%
18
1!
0;
0$
0?
0'
00
07
#300
b1 :
b1 #
1@
1(
1=
1%
18
1!
0,
03
#320
b1 :
b1 #
0@
0(
0=
0%
18
1!
0-
04
#340
1*
11
#350
0*
01
#370
b1 <
1;
1$
1?
1'
b1 :
b1 #
18
1!
10
17
#390
19
1"
0>
0&
b10 :
b10 #
08
0!
0;
0$
0?
0'
b1 B
1*
11
#400
0*
01
#420
b10 <
18
1!
b10 :
b10 #
0>
0&
09
0"
1+
12
#440
b10 :
b10 #
0>
0&
1A
1)
08
0!
1/
16
#460
18
1!
b10 :
b10 #
0>
0&
0A
0)
0/
06
#480
b1 <
19
1"
b10 :
b10 #
0>
0&
08
0!
0+
02
#500
1*
11
#510
0*
01
#530
b10 <
18
1!
b10 :
b10 #
0>
0&
09
0"
1+
12
#550
b11 <
b100 :
b100 #
1>
1&
18
1!
b10 B
1*
11
#560
0*
01
#580
b0 <
19
1"
b100 :
b100 #
08
0!
1.
15
#600
b100 :
b100 #
1A
1)
09
0"
1/
16
#620
19
1"
b100 :
b100 #
0A
0)
0/
06
#640
b10 <
b100 :
b100 #
19
1"
0+
02
#680
1*
11
#690
0*
01
#710
b0 <
b100 :
b100 #
19
1"
1+
12
#730
b1 <
18
1!
1;
1$
1?
1'
b1 :
b1 #
09
0"
b0 B
1*
11
#740
0*
01
#760
b0 <
b1 :
b1 #
18
1!
0;
0$
0?
0'
00
07
#780
b1 <
1;
1$
1?
1'
b1 :
b1 #
18
1!
10
17
#800
b10 <
0>
0&
b10 :
b10 #
18
1!
0;
0$
0?
0'
b1 B
1*
11
#810
0*
01
#850
b0 <
19
1"
b100 :
b100 #
1>
1&
08
0!
b10 B
1*
11
#860
0*
01
#880
b11 <
18
1!
b100 :
b100 #
09
0"
0.
05
#900
0>
0&
b111 :
b111 #
18
1!
b11 B
1*
11
#910
0*
01
#930
19
1"
b111 :
b111 #
0>
0&
08
0!
0+
02
#950
18
1!
b111 :
b111 #
0>
0&
09
0"
1+
12
#970
b111 :
b111 #
0>
0&
1A
1)
08
0!
1/
16
#990
b1 <
b1 :
b1 #
1>
1&
b0 B
1*
11
#1000
0*
01
#1020
18
1!
1;
1$
1?
1'
b1 :
b1 #
0A
0)
0/
06
#1040
b0 <
b1 :
b1 #
18
1!
0;
0$
0?
0'
00
07
